README.md
setup.py
pyewts/ACIP.py
pyewts/__init__.py
pyewts/pyewts.py
pyewts.egg-info/PKG-INFO
pyewts.egg-info/SOURCES.txt
pyewts.egg-info/dependency_links.txt
pyewts.egg-info/top_level.txt