Metadata-Version: 2.1
Name: pyewts
Version: 0.2.0
Summary: Python utils for EWTS conversion from / to Unicode
Home-page: https://github.com/Esukhia/pyewts
Author: Esukhia development team
Author-email: esukhiadev@gmail.com
License: Apache2
Project-URL: Source, https://github.com/Esukhia/pyewts
Project-URL: Tracker, https://github.com/Esukhia/pyewts/issues
Keywords: tibetan
Platform: UNKNOWN
Classifier: Development Status :: 3 - Alpha
Classifier: Topic :: Text Processing :: Linguistic
Classifier: Programming Language :: Python :: 3
Classifier: Operating System :: OS Independent
Classifier: Intended Audience :: Developers
Classifier: Intended Audience :: Science/Research
Classifier: License :: OSI Approved :: Apache Software License
Classifier: Natural Language :: Tibetan
Requires-Python: >=3.4
